tsgettoolbox/CHANGELOG.md
tsgettoolbox/__init__.py
tsgettoolbox/appdirs.py
tsgettoolbox/hydstra_utils.py
tsgettoolbox/tsgettoolbox.py
tsgettoolbox/utils.py
tsgettoolbox/cdo_api_py/setup.py
tsgettoolbox/cdo_api_py/cdo_api_py/Client.py
tsgettoolbox/cdo_api_py/cdo_api_py/__init__.py
tsgettoolbox/cdo_api_py/cdo_api_py/conf.py
tsgettoolbox/cdo_api_py/cdo_api_py/exceptions.py
tsgettoolbox/cdo_api_py/cdo_api_py/util.py
tsgettoolbox/cdo_api_py/docs/example/__init__.py
tsgettoolbox/cdo_api_py/docs/example/dc_weather_data.py
tsgettoolbox/cdo_api_py/tests/__init__.py
tsgettoolbox/functions/__init__.py
tsgettoolbox/functions/cdec.py
tsgettoolbox/functions/coops.py
tsgettoolbox/functions/cpc.py
tsgettoolbox/functions/daymet.py
tsgettoolbox/functions/fawn.py
tsgettoolbox/functions/hydstra.py
tsgettoolbox/functions/ldas.py
tsgettoolbox/functions/metdata.py
tsgettoolbox/functions/modis.py
tsgettoolbox/functions/ncei.py
tsgettoolbox/functions/ndbc.py
tsgettoolbox/functions/nwis.py
tsgettoolbox/functions/rivergages.py
tsgettoolbox/functions/swtwc.py
tsgettoolbox/functions/terraclimate.py
tsgettoolbox/functions/terraclimate19611990.py
tsgettoolbox/functions/terraclimate19812010.py
tsgettoolbox/functions/terraclimate2C.py
tsgettoolbox/functions/terraclimate4C.py
tsgettoolbox/functions/twc.py
tsgettoolbox/functions/unavco.py
tsgettoolbox/station_metadata/gsod_stations.dat
tsgettoolbox/station_metadata/gsod_stations.py
tsgettoolbox/station_metadata/gsom_stations.dat
tsgettoolbox/station_metadata/gsom_stations.py
tsgettoolbox/station_metadata/modis.rst
tsgettoolbox/station_metadata/modis_prepare.py
tsgettoolbox/station_metadata/nwis_pmcodes.dat
tsgettoolbox/station_metadata/station_collector.py
tsgettoolbox/toolbox_utils/docs/conf.py
tsgettoolbox/toolbox_utils/src/toolbox_utils/__init__.py
tsgettoolbox/toolbox_utils/src/toolbox_utils/tsutils.py
tsgettoolbox/toolbox_utils/src/toolbox_utils/readers/__init__.py
tsgettoolbox/toolbox_utils/src/toolbox_utils/readers/hbn.py
tsgettoolbox-26.1.0.dist-info/licenses/LICENSE.txt
tsgettoolbox-26.1.0.dist-info/METADATA
tsgettoolbox-26.1.0.dist-info/WHEEL
tsgettoolbox-26.1.0.dist-info/entry_points.txt
tsgettoolbox-26.1.0.dist-info/top_level.txt
tsgettoolbox-26.1.0.dist-info/RECORD
