Metadata-Version: 2.4
Name: tsgettoolbox
Version: 26.1.0
Summary: Will get time series from different sources on the internet
Author-email: Tim Cera <tim@cerazone.net>
License: BSD-3-Clause
Project-URL: bitbucket, https://bitbucket.org/timcera/tsgettoolbox/src/main/
Project-URL: documentation, https://timcera.bitbucket.io/tsgettoolbox/docs/index.html#tsgettoolbox-documentation
Project-URL: github, https://github.com/timcera/tsgettoolbox
Keywords: rest,time-series,uri,url,web_services
Classifier: Development Status :: 5 - Production/Stable
Classifier: Environment :: Console
Classifier: Intended Audience :: Developers
Classifier: Intended Audience :: End Users/Desktop
Classifier: Intended Audience :: Science/Research
Classifier: License :: OSI Approved :: BSD License
Classifier: Natural Language :: English
Classifier: Operating System :: OS Independent
Classifier: Programming Language :: Python :: 3.8
Classifier: Programming Language :: Python :: 3.9
Classifier: Programming Language :: Python :: 3.10
Classifier: Programming Language :: Python :: 3.11
Classifier: Programming Language :: Python :: 3.12
Classifier: Programming Language :: Python :: 3 :: Only
Classifier: Topic :: Scientific/Engineering
Classifier: Topic :: Scientific/Engineering :: Information Analysis
Classifier: Topic :: Software Development :: Libraries :: Python Modules
Requires-Python: >=3.8
License-File: LICENSE.txt
Requires-Dist: async_retriever
Requires-Dist: beautifulsoup4
Requires-Dist: cftime
Requires-Dist: cltoolbox
Requires-Dist: dateparser
Requires-Dist: geojson
Requires-Dist: haversine
Requires-Dist: httpretty
Requires-Dist: isodate
Requires-Dist: jinja2
Requires-Dist: lxml
Requires-Dist: mechanize
Requires-Dist: numpy<2.0,>=1.20; python_version <= "3.9"
Requires-Dist: packaging
Requires-Dist: pandas[excel]
Requires-Dist: pint!=0.21.*,<0.22; python_version < "3.9"
Requires-Dist: pint-pandas
Requires-Dist: platformdirs
Requires-Dist: pydantic
Requires-Dist: pydap
Requires-Dist: python-dateutil
Requires-Dist: requests
Requires-Dist: scipy
Requires-Dist: siphon
Requires-Dist: suds-community
Requires-Dist: tabulate
Dynamic: license-file
